happydata/__init__.py
happydata/cmd.py
happydata/io.py
happydata/lodash.py
happydata-0.1.0.dist-info/licenses/LICENSE
happydata-0.1.0.dist-info/METADATA
happydata-0.1.0.dist-info/WHEEL
happydata-0.1.0.dist-info/top_level.txt
happydata-0.1.0.dist-info/RECORD
