Metadata-Version: 2.4
Name: happydata
Version: 0.1.0
Summary: data loading,writing, transforming without third party library
Home-page: https://github.com/daqiancode/happydata
Author: Daqian
Platform: Independant
Requires-Python: >=3.12
License-File: LICENSE
Dynamic: author
Dynamic: home-page
Dynamic: license-file
Dynamic: platform
